.gitignore
MANIFEST.in
setup.py
ebs/__init__.py
ebs/linuxnode/__init__.py
ebs/linuxnode/omxplayer.py
ebs/linuxnode/gui/__init__.py
ebs/linuxnode/gui/kivy/__init__.py
ebs/linuxnode/gui/kivy/mediaplayer/__init__.py
ebs/linuxnode/gui/kivy/mediaplayer/omxplayer.py
ebs/linuxnode/gui/kivy/mediaplayer/players/__init__.py
ebs/linuxnode/gui/kivy/mediaplayer/players/omxplayer.py
ebs_linuxnode_rpi_omxplayer.egg-info/PKG-INFO
ebs_linuxnode_rpi_omxplayer.egg-info/SOURCES.txt
ebs_linuxnode_rpi_omxplayer.egg-info/dependency_links.txt
ebs_linuxnode_rpi_omxplayer.egg-info/requires.txt
ebs_linuxnode_rpi_omxplayer.egg-info/top_level.txt